<?xml version="1.0" encoding="utf-8"?>
<lessons banner="bannerL3a">
  <lesson type="standard" narrationFile="L1_U3_10">
    <page file="L1_U3_10(0)" delay="0" />
    <page file="L1_U3_10(1)" delay="8" />
    <page file="L1_U3_10(2)" delay="12" />
    <page file="L1_U3_10(3)" delay="15" />
    <page file="L1_U3_10(4)" delay="22" />
    <page file="L1_U3_10(5)" delay="25" />
    <page file="L1_U3_10(6)" delay="29" />
    <page file="L1_U3_10(7)" delay="31" />
  </lesson>
  <lesson type="MCQ" narrationFile="G_L1_U3_11">
    <page>
      <question image="G_L1_U3_11(1)-Q">
        <option image="G_L1_U3_6-12(1)-A1" answer="false" />
        <option image="G_L1_U3_6-12(1)-A2" answer="false" />
        <option image="G_L1_U3_6-12(1)-A3" answer="false" />
        <option image="G_L1_U3_6-12(1)-A4" answer="correct" />
        <option image="G_L1_U3_6-12(1)-A5" answer="false" />
        <option image="G_L1_U3_6-12(1)-A6" answer="false" />
        <option image="G_L1_U3_6-12(1)-A7" answer="false" />
      </question>
    </page>
  </lesson>
  <lesson type="MCQ" narrationFile="G_L1_U3_12">
    <page>
      <question image="G_L1_U3_12(1)-Q">
        <option image="G_L1_U3_6-12(1)-A1" answer="correct" />
        <option image="G_L1_U3_6-12(1)-A2" answer="false" />
        <option image="G_L1_U3_6-12(1)-A3" answer="false" />
        <option image="G_L1_U3_6-12(1)-A4" answer="false" />
        <option image="G_L1_U3_6-12(1)-A5" answer="false" />
        <option image="G_L1_U3_6-12(1)-A6" answer="false" />
        <option image="G_L1_U3_6-12(1)-A7" answer="false" />
      </question>
    </page>
  </lesson>
</lessons>